{
    "key": "group_6352cb5dd66a6",
    "title": "Social Global",
    "fields": [
        {
            "key": "field_6352cb5ddaa99",
            "label": "Global Social",
            "name": "",
            "type": "tab",
            "instructions": "",
            "required": 0,
            "conditional_logic": 0,
            "wrapper": {
                "width": "",
                "class": "",
                "id": ""
            },
            "placement": "top",
            "endpoint": 0
        },
        {
            "key": "field_6352cb5ddaaa6",
            "label": "Social",
            "name": "options_social_list",
            "type": "checkbox",
            "instructions": "",
            "required": 0,
            "conditional_logic": 0,
            "wrapper": {
                "width": "",
                "class": "",
                "id": ""
            },
            "choices": {
                "fb": "Facebook Social",
                "gg": "Google",
                "tw": "Twitter",
                "yt": "Youtube",
                "in": "Instagram",
                "fl": "Flickr",
                "tu": "Tumblr",
                "pi": "Pinterest",
                "sl": "Slack"
            },
            "default_value": [],
            "return_format": "value",
            "allow_custom": 0,
            "layout": "horizontal",
            "toggle": 1,
            "save_custom": 0
        },
        {
            "key": "field_6352cb5ddaaae",
            "label": "Facebook URL",
            "name": "options_fb_url",
            "type": "text",
            "instructions": "",
            "required": 0,
            "conditional_logic": [
                [
                    {
                        "field": "field_6352cb5ddaaa6",
                        "operator": "==",
                        "value": "fb"
                    }
                ]
            ],
            "wrapper": {
                "width": "",
                "class": "",
                "id": ""
            },
            "default_value": "",
            "maxlength": "",
            "placeholder": "",
            "prepend": "",
            "append": ""
        },
        {
            "key": "field_6352cb5ddaab4",
            "label": "Google URL",
            "name": "options_google_url",
            "type": "text",
            "instructions": "",
            "required": 0,
            "conditional_logic": [
                [
                    {
                        "field": "field_6352cb5ddaaa6",
                        "operator": "==",
                        "value": "gg"
                    }
                ]
            ],
            "wrapper": {
                "width": "",
                "class": "",
                "id": ""
            },
            "default_value": "",
            "maxlength": "",
            "placeholder": "",
            "prepend": "",
            "append": ""
        },
        {
            "key": "field_6352cb5ddaabc",
            "label": "Twitter URL",
            "name": "options_twitter_url",
            "type": "text",
            "instructions": "",
            "required": 0,
            "conditional_logic": [
                [
                    {
                        "field": "field_6352cb5ddaaa6",
                        "operator": "==",
                        "value": "tw"
                    }
                ]
            ],
            "wrapper": {
                "width": "",
                "class": "",
                "id": ""
            },
            "default_value": "",
            "maxlength": "",
            "placeholder": "",
            "prepend": "",
            "append": ""
        },
        {
            "key": "field_6352cb5ddaac2",
            "label": "Youtube URL",
            "name": "options_youtube_url",
            "type": "text",
            "instructions": "",
            "required": 0,
            "conditional_logic": [
                [
                    {
                        "field": "field_6352cb5ddaaa6",
                        "operator": "==",
                        "value": "yt"
                    }
                ]
            ],
            "wrapper": {
                "width": "",
                "class": "",
                "id": ""
            },
            "default_value": "",
            "maxlength": "",
            "placeholder": "",
            "prepend": "",
            "append": ""
        },
        {
            "key": "field_6352cb5ddaace",
            "label": "Instagram URL",
            "name": "options_instagram_url",
            "type": "text",
            "instructions": "",
            "required": 0,
            "conditional_logic": [
                [
                    {
                        "field": "field_6352cb5ddaaa6",
                        "operator": "==",
                        "value": "in"
                    }
                ]
            ],
            "wrapper": {
                "width": "",
                "class": "",
                "id": ""
            },
            "default_value": "",
            "maxlength": "",
            "placeholder": "",
            "prepend": "",
            "append": ""
        },
        {
            "key": "field_6352cb5ddaadc",
            "label": "Flickr URL",
            "name": "options_flickr_url",
            "type": "text",
            "instructions": "",
            "required": 0,
            "conditional_logic": [
                [
                    {
                        "field": "field_6352cb5ddaaa6",
                        "operator": "==",
                        "value": "fl"
                    }
                ]
            ],
            "wrapper": {
                "width": "",
                "class": "",
                "id": ""
            },
            "default_value": "",
            "maxlength": "",
            "placeholder": "",
            "prepend": "",
            "append": ""
        },
        {
            "key": "field_6352cb5ddaafa",
            "label": "Tumblr URL",
            "name": "options_tumblr_url",
            "type": "text",
            "instructions": "",
            "required": 0,
            "conditional_logic": [
                [
                    {
                        "field": "field_6352cb5ddaaa6",
                        "operator": "==",
                        "value": "tu"
                    }
                ]
            ],
            "wrapper": {
                "width": "",
                "class": "",
                "id": ""
            },
            "default_value": "",
            "maxlength": "",
            "placeholder": "",
            "prepend": "",
            "append": ""
        },
        {
            "key": "field_6352cb5ddab06",
            "label": "Pinterest URL",
            "name": "options_pinterest_url",
            "type": "text",
            "instructions": "",
            "required": 0,
            "conditional_logic": [
                [
                    {
                        "field": "field_6352cb5ddaaa6",
                        "operator": "==",
                        "value": "pi"
                    }
                ]
            ],
            "wrapper": {
                "width": "",
                "class": "",
                "id": ""
            },
            "default_value": "",
            "maxlength": "",
            "placeholder": "",
            "prepend": "",
            "append": ""
        },
        {
            "key": "field_6352cb5ddab0b",
            "label": "Slack URL",
            "name": "options_slack_url",
            "type": "text",
            "instructions": "",
            "required": 0,
            "conditional_logic": [
                [
                    {
                        "field": "field_6352cb5ddaaa6",
                        "operator": "==",
                        "value": "sl"
                    }
                ]
            ],
            "wrapper": {
                "width": "",
                "class": "",
                "id": ""
            },
            "default_value": "",
            "maxlength": "",
            "placeholder": "",
            "prepend": "",
            "append": ""
        }
    ],
    "location": [
        [
            {
                "param": "options_page",
                "operator": "==",
                "value": "theme-general-settings"
            }
        ]
    ],
    "menu_order": 0,
    "position": "normal",
    "style": "default",
    "label_placement": "top",
    "instruction_placement": "label",
    "hide_on_screen": "",
    "active": true,
    "description": "",
    "show_in_rest": 0,
    "modified": 1666799729
}